{
    "homeItems": [{
        "header"  : "1. Introduction",
        "content" : [
            "<p>Learn about the basics of app building with Sencha ExtWebComponets</p>",
            "<p><a href='./guides/getting_started.html'>Getting Started</a></p>"
        ],
        "badgeCls"     : "fa fa-info-circle"
    }, {
        "header"  : "2. Core Concepts",
        "content" : [
            "<p>Start learning the core concepts of ExtWebComponets</p>",
            "<p><a href='./guides/packages.html'>ExtWebComponets Packages</a></p>"
        ],
        "badgeCls"     : "fa fa-star"
    }]
}
