{
  "title": "Sencha Architect",

  "headhtml": [
    "<link rel='canonical' href='http://docs.sencha.com/architect/3' /><meta name='description' content='Sencha Architect Documentation from Sencha.' />"
  ],

  "docroot": "http://docs.sencha.com/architect/3/",

  "destination" : {
    "type"  : "path",
    "value" : "./output/architect/"
  },

  "input" : {
    "type"  : "path",
    "value" : "./input/architect-json/"
  },

  "frameworks" : {
    "ext" : "http://docs.sencha.com/extjs/6.0/6.0.1-classic/#!/api/",
    "touch" : "http://docs.sencha.com/extjs/6.0/6.0.1-modern/#!/api/",
    "modern" : "http://docs.sencha.com/extjs/6.0/6.0.1-modern/#!/api/"
  },

  "guides" : {
    "version": "3.0",
    "path"   : "../modules/guides/architect",
    "output" : "guides",
    "template" : "./modules/base/tpls/main.hbs",
    "homeTemplate": "./modules/base/tpls/main.hbs"
  }
}

