{
  "title": "Ext JS",

  "meta" : "Modern Toolkit",

  "otherToolkit" : "classic",
    "otherToolkitConfig" : "classic",

  "headhtml": [
    "<link rel='canonical' href='http://docs.sencha.com/extjs/6.0.1-modern/' /><meta name='description' content='Ext JS Classic API Documentation from Sencha.' />"
  ],

  "docroot": "http://docs.sencha.com/extjs/6.0.1-modern",

  "destination" : {
    "type"  : "path",
    "value" : "./output/extjs/"
  },

  "input" : {
    "type"  : "path",
    "value" : "./input/modern-json/"
  },

  "frameworks" : {
    "ext" : "http://docs.sencha.com/extjs/6.0.1/classic/",
    "touch" : "http://docs.sencha.com/extjs/6.0.1/modern/",
    "modern" : "http://docs.sencha.com/extjs/6.0.1/modern/"
  },

  "guides" : {
    "version": "6.0",
    "path"   : "../modules/guides/extjs",
    "config": "config60.json",
    "output" : "guides",
    "template": "./modules/base/tpls/main.hbs",
    "homeTemplate": "./modules/base/tpls/main.hbs"
  },

  "hasApi" : true,

    "search": {
        "config": "cmd",
        "pversion": "6.x"
    }
}
